topsis/__init__.py
topsis/__main__.py
preksha_topsis-0.0.1.dist-info/LICENSE
preksha_topsis-0.0.1.dist-info/METADATA
preksha_topsis-0.0.1.dist-info/WHEEL
preksha_topsis-0.0.1.dist-info/entry_points.txt
preksha_topsis-0.0.1.dist-info/top_level.txt
preksha_topsis-0.0.1.dist-info/RECORD
